Status/__init__.py
Status/basic_status.py
Status/cpu_status.py
Status/ram_status.py
ant-net-monitor/__init__.py
ant-net-monitor/cli.py
ant-net-monitor/config.py
ant-net-monitor/extensions.py
ant-net-monitor/status.py
ant_net_monitor/__init__.py
ant_net_monitor/cli.py
ant_net_monitor/config.py
ant_net_monitor/extensions.py
ant_net_monitor/status.py
ant_net_monitor/status_blueprint.py
ant_net_monitor/threads.py
ant_net_monitor/Status/__init__.py
ant_net_monitor/Status/basic_status.py
ant_net_monitor/Status/cpu_status.py
ant_net_monitor/Status/ram_status.py
ant_net_monitor/alarm/__init__.py
ant_net_monitor/alarm/alarm.py
ant_net_monitor/alarm/alarm_flag.py
ant_net_monitor/alarm/alarm_item.py
ant_net_monitor/alarm/alarm_log.py
ant_net_monitor/blueprint/__init__.py
ant_net_monitor/blueprint/alarm_blueprint.py
ant_net_monitor/blueprint/status_blueprint.py
ant_net_monitor/dist/favicon.ico
ant_net_monitor/dist/favicon.png
ant_net_monitor/dist/index.html
ant_net_monitor/dist/css/app.64bee21b.css
ant_net_monitor/dist/js/app.16d10ac1.js
ant_net_monitor/dist/js/app.16d10ac1.js.map
ant_net_monitor/dist/js/chunk-vendors.84f5b36d.js
ant_net_monitor/dist/js/chunk-vendors.84f5b36d.js.map
ant_net_monitor/dist/static/css/app.1e58311d.css
ant_net_monitor/dist/static/css/app.4cdca62f.css
ant_net_monitor/dist/static/css/app.64bee21b.css
ant_net_monitor/dist/static/css/app.b8c04424.css
ant_net_monitor/dist/static/css/app.cbab31a6.css
ant_net_monitor/dist/static/css/chunk-09f59638.c9cb48c0.css
ant_net_monitor/dist/static/css/chunk-2d7c4d95.446f49bb.css
ant_net_monitor/dist/static/css/chunk-339089f2.394a4a6f.css
ant_net_monitor/dist/static/css/chunk-35935860.45832aea.css
ant_net_monitor/dist/static/css/chunk-3aa407ba.cc17b018.css
ant_net_monitor/dist/static/css/chunk-619a0c2e.49432284.css
ant_net_monitor/dist/static/css/chunk-675356e1.49432284.css
ant_net_monitor/dist/static/css/chunk-6d982b58.34997099.css
ant_net_monitor/dist/static/css/chunk-8eeae620.30edaac3.css
ant_net_monitor-1.0.0.dist-info/METADATA
ant_net_monitor-1.0.0.dist-info/WHEEL
ant_net_monitor-1.0.0.dist-info/top_level.txt
ant_net_monitor-1.0.0.dist-info/RECORD
