Metadata-Version: 2.1
Name: ant-net-monitor
Version: 1.0.0
Summary: UNKNOWN
Home-page: https://github.com/qzmlgfj/Graduation-Project
License: UNKNOWN
Platform: UNKNOWN
Requires-Python: >=3.8
Requires-Dist: click (>=8.0.3)
Requires-Dist: flask-sqlalchemy (>=2.5.1)
Requires-Dist: flask (>=2.0.2)
Requires-Dist: flask-cors (>=3.0.10)
Requires-Dist: gunicorn (>=20.1.0)
Requires-Dist: psutil (>=5.9.0)
Requires-Dist: pysnmp (>=4.4.12)
